[
  {
    "serial": 0,
    "orderId": null,
    "positionId": 1,
    "event": "Create Position",
    "time": 1641783600000,
    "volume": 11000,
    "quantity": 0.11,
    "type": "Sell",
    "entryPrice": 1.13396,
    "tp": null,
    "sl": null,
    "closePrice": null,
    "grossProfit": 0,
    "pips": 0,
    "balance": null,
    "equity": 10000
  },
  {
    "serial": 1,
    "orderId": null,
    "positionId": 1,
    "event": "Position Modified (S/L)",
    "time": 1641783600000,
    "volume": 11000,
    "quantity": 0.11,
    "type": "Sell",
    "entryPrice": 1.13396,
    "tp": null,
    "sl": 1.15154,
    "closePrice": null,
    "grossProfit": 0,
    "pips": 0,
    "balance": null,
    "equity": 9998.33
  },
  {
    "serial": 2,
    "orderId": null,
    "positionId": 1,
    "event": "Position Modified (T/P)",
    "time": 1641783600000,
    "volume": 11000,
    "quantity": 0.11,
    "type": "Sell",
    "entryPrice": 1.13396,
    "tp": 1.10759,
    "sl": 1.15154,
    "closePrice": null,
    "grossProfit": 0,
    "pips": 0,
    "balance": null,
    "equity": 9998.33
  },
  {
    "serial": 3,
    "orderId": null,
    "positionId": 1,
    "event": "Position closed",
    "time": 1641834000000,
    "volume": 11000,
    "quantity": 0.11,
    "type": "Sell",
    "entryPrice": 1.13396,
    "tp": 1.10759,
    "sl": 1.15154,
    "closePrice": 1.13285,
    "grossProfit": 11.19,
    "pips": 11.1,
    "balance": 10010.53,
    "equity": 10010.53
  },
  {
    "serial": 4,
    "orderId": null,
    "positionId": 2,
    "event": "Create Position",
    "time": 1641870000000,
    "volume": 11000,
    "quantity": 0.11,
    "type": "Sell",
    "entryPrice": 1.1338,
    "tp": null,
    "sl": null,
    "closePrice": null,
    "grossProfit": 0,
    "pips": 0,
    "balance": null,
    "equity": 10010.53
  },
  {
    "serial": 5,
    "orderId": null,
    "positionId": 2,
    "event": "Position Modified (S/L)",
    "time": 1641870000000,
    "volume": 11000,
    "quantity": 0.11,
    "type": "Sell",
    "entryPrice": 1.1338,
    "tp": null,
    "sl": 1.15037,
    "closePrice": null,
    "grossProfit": 0,
    "pips": 0,
    "balance": null,
    "equity": 10008.86
  },
  {
    "serial": 6,
    "orderId": null,
    "positionId": 2,
    "event": "Position Modified (T/P)",
    "time": 1641870000000,
    "volume": 11000,
    "quantity": 0.11,
    "type": "Sell",
    "entryPrice": 1.1338,
    "tp": 1.10894,
    "sl": 1.15037,
    "closePrice": null,
    "grossProfit": 0,
    "pips": 0,
    "balance": null,
    "equity": 10008.86
  },
  {
    "serial": 7,
    "orderId": null,
    "positionId": 2,
    "event": "Position closed",
    "time": 1641920400000,
    "volume": 11000,
    "quantity": 0.11,
    "type": "Sell",
    "entryPrice": 1.1338,
    "tp": 1.10894,
    "sl": 1.15037,
    "closePrice": 1.13629,
    "grossProfit": -25.11,
    "pips": -24.9,
    "balance": 9984.76,
    "equity": 9984.76
  },
  {
    "serial": 8,
    "orderId": null,
    "positionId": 3,
    "event": "Create Position",
    "time": 1641956400000,
    "volume": 11000,
    "quantity": 0.11,
    "type": "Sell",
    "entryPrice": 1.13719,
    "tp": null,
    "sl": null,
    "closePrice": null,
    "grossProfit": 0,
    "pips": 0,
    "balance": null,
    "equity": 9984.76
  },
  {
    "serial": 9,
    "orderId": null,
    "positionId": 3,
    "event": "Position Modified (S/L)",
    "time": 1641956400000,
    "volume": 11000,
    "quantity": 0.11,
    "type": "Sell",
    "entryPrice": 1.13719,
    "tp": null,
    "sl": 1.15432,
    "closePrice": null,
    "grossProfit": 0,
    "pips": 0,
    "balance": null,
    "equity": 9983.09
  },
  {
    "serial": 10,
    "orderId": null,
    "positionId": 3,
    "event": "Position Modified (T/P)",
    "time": 1641956400000,
    "volume": 11000,
    "quantity": 0.11,
    "type": "Sell",
    "entryPrice": 1.13719,
    "tp": 1.1115,
    "sl": 1.15432,
    "closePrice": null,
    "grossProfit": 0,
    "pips": 0,
    "balance": null,
    "equity": 9983.09
  },
  {
    "serial": 11,
    "orderId": null,
    "positionId": 3,
    "event": "Position closed",
    "time": 1642006800000,
    "volume": 11000,
    "quantity": 0.11,
    "type": "Sell",
    "entryPrice": 1.13719,
    "tp": 1.1115,
    "sl": 1.15432,
    "closePrice": 1.14324,
    "grossProfit": -61,
    "pips": -60.5,
    "balance": 9923.1,
    "equity": 9923.1
  },
  {
    "serial": 12,
    "orderId": null,
    "positionId": 4,
    "event": "Create Position",
    "time": 1642042800000,
    "volume": 10000,
    "quantity": 0.1,
    "type": "Sell",
    "entryPrice": 1.1442,
    "tp": null,
    "sl": null,
    "closePrice": null,
    "grossProfit": 0,
    "pips": 0,
    "balance": null,
    "equity": 9923.1
  },
  {
    "serial": 13,
    "orderId": null,
    "positionId": 4,
    "event": "Position Modified (S/L)",
    "time": 1642042800000,
    "volume": 10000,
    "quantity": 0.1,
    "type": "Sell",
    "entryPrice": 1.1442,
    "tp": null,
    "sl": 1.16244,
    "closePrice": null,
    "grossProfit": 0,
    "pips": 0,
    "balance": null,
    "equity": 9921.58
  },
  {
    "serial": 14,
    "orderId": null,
    "positionId": 4,
    "event": "Position Modified (T/P)",
    "time": 1642042800000,
    "volume": 10000,
    "quantity": 0.1,
    "type": "Sell",
    "entryPrice": 1.1442,
    "tp": 1.11685,
    "sl": 1.16244,
    "closePrice": null,
    "grossProfit": 0,
    "pips": 0,
    "balance": null,
    "equity": 9921.58
  },
  {
    "serial": 15,
    "orderId": null,
    "positionId": 4,
    "event": "Position closed",
    "time": 1642093200000,
    "volume": 10000,
    "quantity": 0.1,
    "type": "Sell",
    "entryPrice": 1.1442,
    "tp": 1.11685,
    "sl": 1.16244,
    "closePrice": 1.14664,
    "grossProfit": -22.37,
    "pips": -24.4,
    "balance": 9900.13,
    "equity": 9900.13
  },
  {
    "serial": 16,
    "orderId": null,
    "positionId": 5,
    "event": "Create Position",
    "time": 1643166000000,
    "volume": 11000,
    "quantity": 0.11,
    "type": "Sell",
    "entryPrice": 1.13063,
    "tp": null,
    "sl": null,
    "closePrice": null,
    "grossProfit": 0,
    "pips": 0,
    "balance": null,
    "equity": 9900.13
  },
  {
    "serial": 17,
    "orderId": null,
    "positionId": 5,
    "event": "Position Modified (S/L)",
    "time": 1643166000000,
    "volume": 11000,
    "quantity": 0.11,
    "type": "Sell",
    "entryPrice": 1.13063,
    "tp": null,
    "sl": 1.14767,
    "closePrice": null,
    "grossProfit": 0,
    "pips": 0,
    "balance": null,
    "equity": 9898.46
  },
  {
    "serial": 18,
    "orderId": null,
    "positionId": 5,
    "event": "Position Modified (T/P)",
    "time": 1643166000000,
    "volume": 11000,
    "quantity": 0.11,
    "type": "Sell",
    "entryPrice": 1.13063,
    "tp": 1.10507,
    "sl": 1.14767,
    "closePrice": null,
    "grossProfit": 0,
    "pips": 0,
    "balance": null,
    "equity": 9898.46
  },
  {
    "serial": 19,
    "orderId": null,
    "positionId": 5,
    "event": "Position closed",
    "time": 1643216400000,
    "volume": 11000,
    "quantity": 0.11,
    "type": "Sell",
    "entryPrice": 1.13063,
    "tp": 1.10507,
    "sl": 1.14767,
    "closePrice": 1.12799,
    "grossProfit": 26.62,
    "pips": 26.4,
    "balance": 9926.09,
    "equity": 9926.09
  },
  {
    "serial": 20,
    "orderId": null,
    "positionId": 6,
    "event": "Create Position",
    "time": 1660273200000,
    "volume": 6000,
    "quantity": 0.06,
    "type": "Sell",
    "entryPrice": 1.03113,
    "tp": null,
    "sl": null,
    "closePrice": null,
    "grossProfit": 0,
    "pips": 0,
    "balance": null,
    "equity": 9926.09
  },
  {
    "serial": 21,
    "orderId": null,
    "positionId": 6,
    "event": "Position Modified (S/L)",
    "time": 1660273200000,
    "volume": 6000,
    "quantity": 0.06,
    "type": "Sell",
    "entryPrice": 1.03113,
    "tp": null,
    "sl": 1.05944,
    "closePrice": null,
    "grossProfit": 0,
    "pips": 0,
    "balance": null,
    "equity": 9925.18
  },
  {
    "serial": 22,
    "orderId": null,
    "positionId": 6,
    "event": "Position Modified (T/P)",
    "time": 1660273200000,
    "volume": 6000,
    "quantity": 0.06,
    "type": "Sell",
    "entryPrice": 1.03113,
    "tp": 0.98867,
    "sl": 1.05944,
    "closePrice": null,
    "grossProfit": 0,
    "pips": 0,
    "balance": null,
    "equity": 9925.18
  },
  {
    "serial": 23,
    "orderId": null,
    "positionId": 6,
    "event": "Position closed",
    "time": 1660323600000,
    "volume": 6000,
    "quantity": 0.06,
    "type": "Sell",
    "entryPrice": 1.03113,
    "tp": 0.98867,
    "sl": 1.05944,
    "closePrice": 1.02575,
    "grossProfit": 29.59,
    "pips": 53.8,
    "balance": 9955.32,
    "equity": 9955.32
  },
  {
    "serial": 24,
    "orderId": null,
    "positionId": 7,
    "event": "Create Position",
    "time": 1660532400000,
    "volume": 7000,
    "quantity": 0.07,
    "type": "Sell",
    "entryPrice": 1.02454,
    "tp": null,
    "sl": null,
    "closePrice": null,
    "grossProfit": 0,
    "pips": 0,
    "balance": null,
    "equity": 9955.32
  },
  {
    "serial": 25,
    "orderId": null,
    "positionId": 7,
    "event": "Position Modified (S/L)",
    "time": 1660532400000,
    "volume": 7000,
    "quantity": 0.07,
    "type": "Sell",
    "entryPrice": 1.02454,
    "tp": null,
    "sl": 1.04991,
    "closePrice": null,
    "grossProfit": 0,
    "pips": 0,
    "balance": null,
    "equity": 9954.26
  },
  {
    "serial": 26,
    "orderId": null,
    "positionId": 7,
    "event": "Position Modified (T/P)",
    "time": 1660532400000,
    "volume": 7000,
    "quantity": 0.07,
    "type": "Sell",
    "entryPrice": 1.02454,
    "tp": 0.98649,
    "sl": 1.04991,
    "closePrice": null,
    "grossProfit": 0,
    "pips": 0,
    "balance": null,
    "equity": 9954.26
  },
  {
    "serial": 27,
    "orderId": null,
    "positionId": 7,
    "event": "Position closed",
    "time": 1660582800000,
    "volume": 7000,
    "quantity": 0.07,
    "type": "Sell",
    "entryPrice": 1.02454,
    "tp": 0.98649,
    "sl": 1.04991,
    "closePrice": 1.01767,
    "grossProfit": 44.08,
    "pips": 68.7,
    "balance": 9998.98,
    "equity": 9998.98
  },
  {
    "serial": 28,
    "orderId": null,
    "positionId": 8,
    "event": "Create Position",
    "time": 1660618800000,
    "volume": 7000,
    "quantity": 0.07,
    "type": "Sell",
    "entryPrice": 1.01691,
    "tp": null,
    "sl": null,
    "closePrice": null,
    "grossProfit": 0,
    "pips": 0,
    "balance": null,
    "equity": 9998.98
  },
  {
    "serial": 29,
    "orderId": null,
    "positionId": 8,
    "event": "Position Modified (S/L)",
    "time": 1660618800000,
    "volume": 7000,
    "quantity": 0.07,
    "type": "Sell",
    "entryPrice": 1.01691,
    "tp": null,
    "sl": 1.0436,
    "closePrice": null,
    "grossProfit": 0,
    "pips": 0,
    "balance": null,
    "equity": 9997.92
  },
  {
    "serial": 30,
    "orderId": null,
    "positionId": 8,
    "event": "Position Modified (T/P)",
    "time": 1660618800000,
    "volume": 7000,
    "quantity": 0.07,
    "type": "Sell",
    "entryPrice": 1.01691,
    "tp": 0.97688,
    "sl": 1.0436,
    "closePrice": null,
    "grossProfit": 0,
    "pips": 0,
    "balance": null,
    "equity": 9997.92
  },
  {
    "serial": 31,
    "orderId": null,
    "positionId": 8,
    "event": "Position closed",
    "time": 1660669200000,
    "volume": 7000,
    "quantity": 0.07,
    "type": "Sell",
    "entryPrice": 1.01691,
    "tp": 0.97688,
    "sl": 1.0436,
    "closePrice": 1.01669,
    "grossProfit": 1.41,
    "pips": 2.2,
    "balance": 9999.97,
    "equity": 9999.97
  },
  {
    "serial": 32,
    "orderId": null,
    "positionId": 9,
    "event": "Create Position",
    "time": 1660705200000,
    "volume": 7000,
    "quantity": 0.07,
    "type": "Sell",
    "entryPrice": 1.01737,
    "tp": null,
    "sl": null,
    "closePrice": null,
    "grossProfit": 0,
    "pips": 0,
    "balance": null,
    "equity": 9999.97
  },
  {
    "serial": 33,
    "orderId": null,
    "positionId": 9,
    "event": "Position Modified (S/L)",
    "time": 1660705200000,
    "volume": 7000,
    "quantity": 0.07,
    "type": "Sell",
    "entryPrice": 1.01737,
    "tp": null,
    "sl": 1.04441,
    "closePrice": null,
    "grossProfit": 0,
    "pips": 0,
    "balance": null,
    "equity": 9998.91
  },
  {
    "serial": 34,
    "orderId": null,
    "positionId": 9,
    "event": "Position Modified (T/P)",
    "time": 1660705200000,
    "volume": 7000,
    "quantity": 0.07,
    "type": "Sell",
    "entryPrice": 1.01737,
    "tp": 0.97681,
    "sl": 1.04441,
    "closePrice": null,
    "grossProfit": 0,
    "pips": 0,
    "balance": null,
    "equity": 9998.91
  },
  {
    "serial": 35,
    "orderId": null,
    "positionId": 9,
    "event": "Position closed",
    "time": 1660755600000,
    "volume": 7000,
    "quantity": 0.07,
    "type": "Sell",
    "entryPrice": 1.01737,
    "tp": 0.97681,
    "sl": 1.04441,
    "closePrice": 1.01663,
    "grossProfit": 4.75,
    "pips": 7.4,
    "balance": 10004.3,
    "equity": 10004.3
  },
  {
    "serial": 36,
    "orderId": null,
    "positionId": 10,
    "event": "Create Position",
    "time": 1660791600000,
    "volume": 7000,
    "quantity": 0.07,
    "type": "Sell",
    "entryPrice": 1.01805,
    "tp": null,
    "sl": null,
    "closePrice": null,
    "grossProfit": 0,
    "pips": 0,
    "balance": null,
    "equity": 10004.3
  },
  {
    "serial": 37,
    "orderId": null,
    "positionId": 10,
    "event": "Position Modified (S/L)",
    "time": 1660791600000,
    "volume": 7000,
    "quantity": 0.07,
    "type": "Sell",
    "entryPrice": 1.01805,
    "tp": null,
    "sl": 1.04325,
    "closePrice": null,
    "grossProfit": 0,
    "pips": 0,
    "balance": null,
    "equity": 10003.24
  },
  {
    "serial": 38,
    "orderId": null,
    "positionId": 10,
    "event": "Position Modified (T/P)",
    "time": 1660791600000,
    "volume": 7000,
    "quantity": 0.07,
    "type": "Sell",
    "entryPrice": 1.01805,
    "tp": 0.98025,
    "sl": 1.04325,
    "closePrice": null,
    "grossProfit": 0,
    "pips": 0,
    "balance": null,
    "equity": 10003.24
  },
  {
    "serial": 39,
    "orderId": null,
    "positionId": 10,
    "event": "Position closed",
    "time": 1660842000000,
    "volume": 7000,
    "quantity": 0.07,
    "type": "Sell",
    "entryPrice": 1.01805,
    "tp": 0.98025,
    "sl": 1.04325,
    "closePrice": 1.00911,
    "grossProfit": 57.36,
    "pips": 89.4,
    "balance": 10061.24,
    "equity": 10061.24
  },
  {
    "serial": 40,
    "orderId": null,
    "positionId": 11,
    "event": "Create Position",
    "time": 1660878000000,
    "volume": 7000,
    "quantity": 0.07,
    "type": "Sell",
    "entryPrice": 1.00859,
    "tp": null,
    "sl": null,
    "closePrice": null,
    "grossProfit": 0,
    "pips": 0,
    "balance": null,
    "equity": 10061.24
  },
  {
    "serial": 41,
    "orderId": null,
    "positionId": 11,
    "event": "Position Modified (S/L)",
    "time": 1660878000000,
    "volume": 7000,
    "quantity": 0.07,
    "type": "Sell",
    "entryPrice": 1.00859,
    "tp": null,
    "sl": 1.03526,
    "closePrice": null,
    "grossProfit": 0,
    "pips": 0,
    "balance": null,
    "equity": 10060.18
  },
  {
    "serial": 42,
    "orderId": null,
    "positionId": 11,
    "event": "Position Modified (T/P)",
    "time": 1660878000000,
    "volume": 7000,
    "quantity": 0.07,
    "type": "Sell",
    "entryPrice": 1.00859,
    "tp": 0.96858,
    "sl": 1.03526,
    "closePrice": null,
    "grossProfit": 0,
    "pips": 0,
    "balance": null,
    "equity": 10060.18
  },
  {
    "serial": 43,
    "orderId": null,
    "positionId": 11,
    "event": "Position closed",
    "time": 1660903260000,
    "volume": 7000,
    "quantity": 0.07,
    "type": "Sell",
    "entryPrice": 1.00859,
    "tp": 0.96858,
    "sl": 1.03526,
    "closePrice": 1.00699,
    "grossProfit": 10.27,
    "pips": 16,
    "balance": 10071.09,
    "equity": 10071.09
  },
  {
    "serial": 44,
    "orderId": null,
    "positionId": 12,
    "event": "Create Position",
    "time": 1660903260000,
    "volume": 7000,
    "quantity": 0.07,
    "type": "Sell",
    "entryPrice": 1.00689,
    "tp": null,
    "sl": null,
    "closePrice": null,
    "grossProfit": 0,
    "pips": 0,
    "balance": null,
    "equity": 10071.09
  },
  {
    "serial": 45,
    "orderId": null,
    "positionId": 12,
    "event": "Position Modified (S/L)",
    "time": 1660903260000,
    "volume": 7000,
    "quantity": 0.07,
    "type": "Sell",
    "entryPrice": 1.00689,
    "tp": null,
    "sl": 1.03359,
    "closePrice": null,
    "grossProfit": 0,
    "pips": 0,
    "balance": null,
    "equity": 10070.03
  },
  {
    "serial": 46,
    "orderId": null,
    "positionId": 12,
    "event": "Position Modified (T/P)",
    "time": 1660903260000,
    "volume": 7000,
    "quantity": 0.07,
    "type": "Sell",
    "entryPrice": 1.00689,
    "tp": 0.96684,
    "sl": 1.03359,
    "closePrice": null,
    "grossProfit": 0,
    "pips": 0,
    "balance": null,
    "equity": 10070.03
  },
  {
    "serial": 47,
    "orderId": null,
    "positionId": 12,
    "event": "Position closed",
    "time": 1660903320000,
    "volume": 7000,
    "quantity": 0.07,
    "type": "Sell",
    "entryPrice": 1.00689,
    "tp": 0.96684,
    "sl": 1.03359,
    "closePrice": 1.00694,
    "grossProfit": -0.32,
    "pips": -0.5,
    "balance": 10070.35,
    "equity": 10070.35
  },
  {
    "serial": 48,
    "orderId": null,
    "positionId": 13,
    "event": "Create Position",
    "time": 1667227140000,
    "volume": 5000,
    "quantity": 0.05,
    "type": "Sell",
    "entryPrice": 0.98825,
    "tp": null,
    "sl": null,
    "closePrice": null,
    "grossProfit": 0,
    "pips": 0,
    "balance": null,
    "equity": 10070.35
  },
  {
    "serial": 49,
    "orderId": null,
    "positionId": 13,
    "event": "Position Modified (S/L)",
    "time": 1667227140000,
    "volume": 5000,
    "quantity": 0.05,
    "type": "Sell",
    "entryPrice": 0.98825,
    "tp": null,
    "sl": 1.02361,
    "closePrice": null,
    "grossProfit": 0,
    "pips": 0,
    "balance": null,
    "equity": 10069.59
  },
  {
    "serial": 50,
    "orderId": null,
    "positionId": 13,
    "event": "Position Modified (T/P)",
    "time": 1667227140000,
    "volume": 5000,
    "quantity": 0.05,
    "type": "Sell",
    "entryPrice": 0.98825,
    "tp": 0.93521,
    "sl": 1.02361,
    "closePrice": null,
    "grossProfit": 0,
    "pips": 0,
    "balance": null,
    "equity": 10069.59
  },
  {
    "serial": 51,
    "orderId": null,
    "positionId": 13,
    "event": "Position closed",
    "time": 1667235600000,
    "volume": 5000,
    "quantity": 0.05,
    "type": "Sell",
    "entryPrice": 0.98825,
    "tp": 0.93521,
    "sl": 1.02361,
    "closePrice": 0.98764,
    "grossProfit": 2.8,
    "pips": 6.1,
    "balance": 10072.85,
    "equity": 10072.85
  }
]